cli_box.py
cli_box-0.2.0.dist-info/WHEEL
cli_box-0.2.0.dist-info/METADATA
cli_box-0.2.0.dist-info/RECORD
